azure/mgmt/mysqlflexibleservers/__init__.py
azure/mgmt/mysqlflexibleservers/_configuration.py
azure/mgmt/mysqlflexibleservers/_my_sql_management_client.py
azure/mgmt/mysqlflexibleservers/_patch.py
azure/mgmt/mysqlflexibleservers/_serialization.py
azure/mgmt/mysqlflexibleservers/_version.py
azure/mgmt/mysqlflexibleservers/py.typed
azure/mgmt/mysqlflexibleservers/aio/__init__.py
azure/mgmt/mysqlflexibleservers/aio/_configuration.py
azure/mgmt/mysqlflexibleservers/aio/_my_sql_management_client.py
azure/mgmt/mysqlflexibleservers/aio/_patch.py
azure/mgmt/mysqlflexibleservers/aio/operations/__init__.py
azure/mgmt/mysqlflexibleservers/aio/operations/_advanced_threat_protection_settings_operations.py
azure/mgmt/mysqlflexibleservers/aio/operations/_azure_ad_administrators_operations.py
azure/mgmt/mysqlflexibleservers/aio/operations/_backup_and_export_operations.py
azure/mgmt/mysqlflexibleservers/aio/operations/_backups_operations.py
azure/mgmt/mysqlflexibleservers/aio/operations/_check_name_availability_operations.py
azure/mgmt/mysqlflexibleservers/aio/operations/_check_name_availability_without_location_operations.py
azure/mgmt/mysqlflexibleservers/aio/operations/_check_virtual_network_subnet_usage_operations.py
azure/mgmt/mysqlflexibleservers/aio/operations/_configurations_operations.py
azure/mgmt/mysqlflexibleservers/aio/operations/_databases_operations.py
azure/mgmt/mysqlflexibleservers/aio/operations/_firewall_rules_operations.py
azure/mgmt/mysqlflexibleservers/aio/operations/_get_private_dns_zone_suffix_operations.py
azure/mgmt/mysqlflexibleservers/aio/operations/_location_based_capabilities_operations.py
azure/mgmt/mysqlflexibleservers/aio/operations/_location_based_capability_set_operations.py
azure/mgmt/mysqlflexibleservers/aio/operations/_log_files_operations.py
azure/mgmt/mysqlflexibleservers/aio/operations/_long_running_backup_operations.py
azure/mgmt/mysqlflexibleservers/aio/operations/_long_running_backups_operations.py
azure_mgmt_mysqlflexibleservers-1.0.0b3.dist-info/LICENSE
azure_mgmt_mysqlflexibleservers-1.0.0b3.dist-info/METADATA
azure_mgmt_mysqlflexibleservers-1.0.0b3.dist-info/WHEEL
azure_mgmt_mysqlflexibleservers-1.0.0b3.dist-info/top_level.txt
azure_mgmt_mysqlflexibleservers-1.0.0b3.dist-info/RECORD
